gmalg/__init__.py
gmalg/base.py
gmalg/blockcipher.py
gmalg/ellipticcurve.py
gmalg/errors.py
gmalg/primefield.py
gmalg/sm2.py
gmalg/sm3.py
gmalg/sm4.py
gmalg/sm9.py
gmalg/utils.py
gmalg/zuc.py
gmalg-1.1.0.dist-info/licenses/LICENSE
gmalg-1.1.0.dist-info/METADATA
gmalg-1.1.0.dist-info/WHEEL
gmalg-1.1.0.dist-info/top_level.txt
gmalg-1.1.0.dist-info/RECORD
