Metadata-Version: 2.4
Name: gmalg
Version: 1.1.0
Summary: GM algorithms implemented in pure Python.
Author-email: ww-rm <ww-rm@qq.com>
Project-URL: Homepage, https://github.com/ww-rm/gmalg
Project-URL: Issues, https://github.com/ww-rm/gmalg/issues
Project-URL: Documentation, https://gmalg.readthedocs.io
Classifier: Programming Language :: Python :: 3
Classifier: License :: OSI Approved :: MIT License
Classifier: Operating System :: OS Independent
Classifier: Topic :: Security :: Cryptography
Requires-Python: >=3.7
License-File: LICENSE
Dynamic: license-file
